setup.py
immortalmodel/__init__.py
immortalmodel/admin.py
immortalmodel/models.py
immortalmodel/tests.py
twentytab_immortalmodel.egg-info/PKG-INFO
twentytab_immortalmodel.egg-info/SOURCES.txt
twentytab_immortalmodel.egg-info/dependency_links.txt
twentytab_immortalmodel.egg-info/requires.txt
twentytab_immortalmodel.egg-info/top_level.txt