Metadata-Version: 1.0
Name: twentytab-immortalmodel
Version: 0.5
Summary: A django model, manager and queryset implementing undeletable models
Home-page: https://github.com/20tab/twentytab-immortalmodel
Author: 20Tab S.r.l.
Author-email: info@20tab.com
License: MIT License
Platform: UNKNOWN
